{
	"configurations" : 
	[
		{
			"abstractTargets" : 
			[
				{
					"directoryIndex" : 0,
					"id" : "Python3::Interpreter::@6890427a1f51a3e7e1df",
					"jsonFile" : "target-Python3__Interpreter-07e11422a386494be608.json",
					"name" : "Python3::Interpreter",
					"projectIndex" : 0
				},
				{
					"directoryIndex" : 0,
					"id" : "Python3::InterpreterMultiConfig::@6890427a1f51a3e7e1df",
					"jsonFile" : "target-Python3__InterpreterMultiConfig-365a145a17514c44ecc7.json",
					"name" : "Python3::InterpreterMultiConfig",
					"projectIndex" : 0
				},
				{
					"directoryIndex" : 0,
					"id" : "Python::Interpreter::@6890427a1f51a3e7e1df",
					"jsonFile" : "target-Python__Interpreter-89918dd91de67f630616.json",
					"name" : "Python::Interpreter",
					"projectIndex" : 0
				},
				{
					"directoryIndex" : 0,
					"id" : "Python::InterpreterMultiConfig::@6890427a1f51a3e7e1df",
					"jsonFile" : "target-Python__InterpreterMultiConfig-b73746136b464d563b45.json",
					"name" : "Python::InterpreterMultiConfig",
					"projectIndex" : 0
				},
				{
					"directoryIndex" : 0,
					"id" : "Python::Module::@6890427a1f51a3e7e1df",
					"jsonFile" : "target-Python__Module-ee50ba4b25411a16ba94.json",
					"name" : "Python::Module",
					"projectIndex" : 0
				},
				{
					"directoryIndex" : 0,
					"id" : "Python::NumPy::@6890427a1f51a3e7e1df",
					"jsonFile" : "target-Python__NumPy-206031843563b81b7b67.json",
					"name" : "Python::NumPy",
					"projectIndex" : 0
				},
				{
					"directoryIndex" : 0,
					"id" : "Python::Python::@6890427a1f51a3e7e1df",
					"jsonFile" : "target-Python__Python-9aabc99010dc1de6356a.json",
					"name" : "Python::Python",
					"projectIndex" : 0
				},
				{
					"directoryIndex" : 0,
					"id" : "fastcdr::@6890427a1f51a3e7e1df",
					"jsonFile" : "target-fastcdr-ff3e6ba5a107a498215b.json",
					"name" : "fastcdr",
					"projectIndex" : 0
				},
				{
					"directoryIndex" : 0,
					"id" : "rcpputils::rcpputils::@6890427a1f51a3e7e1df",
					"jsonFile" : "target-rcpputils__rcpputils-b1bb167a34cd3898d380.json",
					"name" : "rcpputils::rcpputils",
					"projectIndex" : 0
				},
				{
					"directoryIndex" : 0,
					"id" : "rcutils::rcutils::@6890427a1f51a3e7e1df",
					"jsonFile" : "target-rcutils__rcutils-e05157e16053c0b6453d.json",
					"name" : "rcutils::rcutils",
					"projectIndex" : 0
				},
				{
					"directoryIndex" : 0,
					"id" : "rmw::rmw::@6890427a1f51a3e7e1df",
					"jsonFile" : "target-rmw__rmw-3b8722478cea71025f7d.json",
					"name" : "rmw::rmw",
					"projectIndex" : 0
				},
				{
					"directoryIndex" : 0,
					"id" : "rosidl_runtime_c::rosidl_runtime_c::@6890427a1f51a3e7e1df",
					"jsonFile" : "target-rosidl_runtime_c__rosidl_runtime_c-508f438189df30fe33bf.json",
					"name" : "rosidl_runtime_c::rosidl_runtime_c",
					"projectIndex" : 0
				},
				{
					"directoryIndex" : 0,
					"id" : "rosidl_runtime_cpp::rosidl_runtime_cpp::@6890427a1f51a3e7e1df",
					"jsonFile" : "target-rosidl_runtime_cpp__rosidl_runtime_cpp-deda47fdd672b4b2c959.json",
					"name" : "rosidl_runtime_cpp::rosidl_runtime_cpp",
					"projectIndex" : 0
				},
				{
					"directoryIndex" : 0,
					"id" : "rosidl_typesupport_c::rosidl_typesupport_c::@6890427a1f51a3e7e1df",
					"jsonFile" : "target-rosidl_typesupport_c__rosidl_typesupport_c-d0bb885a9d9e6ebcd81f.json",
					"name" : "rosidl_typesupport_c::rosidl_typesupport_c",
					"projectIndex" : 0
				},
				{
					"directoryIndex" : 0,
					"id" : "rosidl_typesupport_cpp::rosidl_typesupport_cpp::@6890427a1f51a3e7e1df",
					"jsonFile" : "target-rosidl_typesupport_cpp__rosidl_typesupport_cpp-46e0008e27c93d61febe.json",
					"name" : "rosidl_typesupport_cpp::rosidl_typesupport_cpp",
					"projectIndex" : 0
				},
				{
					"directoryIndex" : 0,
					"id" : "rosidl_typesupport_fastrtps_c::rosidl_typesupport_fastrtps_c::@6890427a1f51a3e7e1df",
					"jsonFile" : "target-rosidl_typesupport_fastrtps_c__rosidl_typesupport_fastrtps_c-57671512941699f5e87c.json",
					"name" : "rosidl_typesupport_fastrtps_c::rosidl_typesupport_fastrtps_c",
					"projectIndex" : 0
				},
				{
					"directoryIndex" : 0,
					"id" : "rosidl_typesupport_fastrtps_cpp::rosidl_typesupport_fastrtps_cpp::@6890427a1f51a3e7e1df",
					"jsonFile" : "target-rosidl_typesupport_fastrtps_cpp__rosidl_typesupport_fastrtps_cpp-180be4cf31978cd55871.json",
					"name" : "rosidl_typesupport_fastrtps_cpp::rosidl_typesupport_fastrtps_cpp",
					"projectIndex" : 0
				},
				{
					"directoryIndex" : 0,
					"id" : "rosidl_typesupport_interface::rosidl_typesupport_interface::@6890427a1f51a3e7e1df",
					"jsonFile" : "target-rosidl_typesupport_interface__rosidl_typesupport_interface-e412670e9beb6a848aa2.json",
					"name" : "rosidl_typesupport_interface::rosidl_typesupport_interface",
					"projectIndex" : 0
				},
				{
					"directoryIndex" : 0,
					"id" : "rosidl_typesupport_introspection_c::rosidl_typesupport_introspection_c::@6890427a1f51a3e7e1df",
					"jsonFile" : "target-rosidl_typesupport_introspection_c__rosidl_typesupport_introspection_c-562c789def8fe1a4babf.json",
					"name" : "rosidl_typesupport_introspection_c::rosidl_typesupport_introspection_c",
					"projectIndex" : 0
				},
				{
					"directoryIndex" : 0,
					"id" : "rosidl_typesupport_introspection_cpp::rosidl_typesupport_introspection_cpp::@6890427a1f51a3e7e1df",
					"jsonFile" : "target-rosidl_typesupport_introspection_cpp__rosidl_typesupport_introspection_cpp-0c2d8fdb64d010fe1cb9.json",
					"name" : "rosidl_typesupport_introspection_cpp::rosidl_typesupport_introspection_cpp",
					"projectIndex" : 0
				},
				{
					"directoryIndex" : 0,
					"id" : "unitree_go__rosidl_generator_cpp::@6890427a1f51a3e7e1df",
					"jsonFile" : "target-unitree_go__rosidl_generator_cpp-227f20ccb51f14f24001.json",
					"name" : "unitree_go__rosidl_generator_cpp",
					"projectIndex" : 0
				}
			],
			"directories" : 
			[
				{
					"abstractTargetIndexes" : 
					[
						0,
						1,
						2,
						3,
						4,
						5,
						6,
						7,
						8,
						9,
						10,
						11,
						12,
						13,
						14,
						15,
						16,
						17,
						18,
						19,
						20
					],
					"build" : ".",
					"childIndexes" : 
					[
						1
					],
					"hasInstallRule" : true,
					"jsonFile" : "directory-.-abeb6ced8f174c140970.json",
					"minimumCMakeVersion" : 
					{
						"string" : "3.12"
					},
					"projectIndex" : 0,
					"source" : ".",
					"targetIndexes" : 
					[
						0,
						1,
						2,
						3,
						4,
						5,
						7,
						8,
						9,
						10,
						11,
						12,
						13,
						14,
						15,
						16,
						17,
						18
					]
				},
				{
					"build" : "unitree_go__py",
					"jsonFile" : "directory-unitree_go__py-70af453dfd1a1ff336e1.json",
					"minimumCMakeVersion" : 
					{
						"string" : "3.12"
					},
					"parentIndex" : 0,
					"projectIndex" : 0,
					"source" : "/home/jnu/isaac_ws/build/unitree_go/unitree_go__py",
					"targetIndexes" : 
					[
						6
					]
				}
			],
			"name" : "",
			"projects" : 
			[
				{
					"abstractTargetIndexes" : 
					[
						0,
						1,
						2,
						3,
						4,
						5,
						6,
						7,
						8,
						9,
						10,
						11,
						12,
						13,
						14,
						15,
						16,
						17,
						18,
						19,
						20
					],
					"directoryIndexes" : 
					[
						0,
						1
					],
					"name" : "unitree_go",
					"targetIndexes" : 
					[
						0,
						1,
						2,
						3,
						4,
						5,
						6,
						7,
						8,
						9,
						10,
						11,
						12,
						13,
						14,
						15,
						16,
						17,
						18
					]
				}
			],
			"targets" : 
			[
				{
					"directoryIndex" : 0,
					"id" : "ament_cmake_python_build_unitree_go_egg::@6890427a1f51a3e7e1df",
					"jsonFile" : "target-ament_cmake_python_build_unitree_go_egg-931ee09c5a63335213ee.json",
					"name" : "ament_cmake_python_build_unitree_go_egg",
					"projectIndex" : 0
				},
				{
					"directoryIndex" : 0,
					"id" : "ament_cmake_python_copy_unitree_go::@6890427a1f51a3e7e1df",
					"jsonFile" : "target-ament_cmake_python_copy_unitree_go-7ebafa6d753474a420f2.json",
					"name" : "ament_cmake_python_copy_unitree_go",
					"projectIndex" : 0
				},
				{
					"directoryIndex" : 0,
					"id" : "uninstall::@6890427a1f51a3e7e1df",
					"jsonFile" : "target-uninstall-fdbfd14772c2b2318c87.json",
					"name" : "uninstall",
					"projectIndex" : 0
				},
				{
					"directoryIndex" : 0,
					"id" : "unitree_go::@6890427a1f51a3e7e1df",
					"jsonFile" : "target-unitree_go-31ae4b8c0aa6617e01c3.json",
					"name" : "unitree_go",
					"projectIndex" : 0
				},
				{
					"directoryIndex" : 0,
					"id" : "unitree_go__cpp::@6890427a1f51a3e7e1df",
					"jsonFile" : "target-unitree_go__cpp-3115635d5543c7447dbd.json",
					"name" : "unitree_go__cpp",
					"projectIndex" : 0
				},
				{
					"directoryIndex" : 0,
					"id" : "unitree_go__dds_connext_idl::@6890427a1f51a3e7e1df",
					"jsonFile" : "target-unitree_go__dds_connext_idl-07c5176bce7fcc485a05.json",
					"name" : "unitree_go__dds_connext_idl",
					"projectIndex" : 0
				},
				{
					"directoryIndex" : 1,
					"id" : "unitree_go__py::@38a1591e0fd21223daaf",
					"jsonFile" : "target-unitree_go__py-87106f4825e0fea72a66.json",
					"name" : "unitree_go__py",
					"projectIndex" : 0
				},
				{
					"directoryIndex" : 0,
					"id" : "unitree_go__rosidl_generator_c::@6890427a1f51a3e7e1df",
					"jsonFile" : "target-unitree_go__rosidl_generator_c-883175ede2454cbec648.json",
					"name" : "unitree_go__rosidl_generator_c",
					"projectIndex" : 0
				},
				{
					"directoryIndex" : 0,
					"id" : "unitree_go__rosidl_generator_py::@6890427a1f51a3e7e1df",
					"jsonFile" : "target-unitree_go__rosidl_generator_py-a4803d2d96ae0aea9ec7.json",
					"name" : "unitree_go__rosidl_generator_py",
					"projectIndex" : 0
				},
				{
					"directoryIndex" : 0,
					"id" : "unitree_go__rosidl_typesupport_c::@6890427a1f51a3e7e1df",
					"jsonFile" : "target-unitree_go__rosidl_typesupport_c-4ec847d0e13305245784.json",
					"name" : "unitree_go__rosidl_typesupport_c",
					"projectIndex" : 0
				},
				{
					"directoryIndex" : 0,
					"id" : "unitree_go__rosidl_typesupport_c__pyext::@6890427a1f51a3e7e1df",
					"jsonFile" : "target-unitree_go__rosidl_typesupport_c__pyext-bf42426a12d9b6ce0911.json",
					"name" : "unitree_go__rosidl_typesupport_c__pyext",
					"projectIndex" : 0
				},
				{
					"directoryIndex" : 0,
					"id" : "unitree_go__rosidl_typesupport_cpp::@6890427a1f51a3e7e1df",
					"jsonFile" : "target-unitree_go__rosidl_typesupport_cpp-b51024f4b9155fbbf891.json",
					"name" : "unitree_go__rosidl_typesupport_cpp",
					"projectIndex" : 0
				},
				{
					"directoryIndex" : 0,
					"id" : "unitree_go__rosidl_typesupport_fastrtps_c::@6890427a1f51a3e7e1df",
					"jsonFile" : "target-unitree_go__rosidl_typesupport_fastrtps_c-b97ad6658a40e2dcdd67.json",
					"name" : "unitree_go__rosidl_typesupport_fastrtps_c",
					"projectIndex" : 0
				},
				{
					"directoryIndex" : 0,
					"id" : "unitree_go__rosidl_typesupport_fastrtps_c__pyext::@6890427a1f51a3e7e1df",
					"jsonFile" : "target-unitree_go__rosidl_typesupport_fastrtps_c__pyext-ebf67da01bf9eab3da02.json",
					"name" : "unitree_go__rosidl_typesupport_fastrtps_c__pyext",
					"projectIndex" : 0
				},
				{
					"directoryIndex" : 0,
					"id" : "unitree_go__rosidl_typesupport_fastrtps_cpp::@6890427a1f51a3e7e1df",
					"jsonFile" : "target-unitree_go__rosidl_typesupport_fastrtps_cpp-20649fe75b26936f32cc.json",
					"name" : "unitree_go__rosidl_typesupport_fastrtps_cpp",
					"projectIndex" : 0
				},
				{
					"directoryIndex" : 0,
					"id" : "unitree_go__rosidl_typesupport_introspection_c::@6890427a1f51a3e7e1df",
					"jsonFile" : "target-unitree_go__rosidl_typesupport_introspection_c-c196a1631577f08f8063.json",
					"name" : "unitree_go__rosidl_typesupport_introspection_c",
					"projectIndex" : 0
				},
				{
					"directoryIndex" : 0,
					"id" : "unitree_go__rosidl_typesupport_introspection_c__pyext::@6890427a1f51a3e7e1df",
					"jsonFile" : "target-unitree_go__rosidl_typesupport_introspection_c__pyext-cd94d7528385c861c7cd.json",
					"name" : "unitree_go__rosidl_typesupport_introspection_c__pyext",
					"projectIndex" : 0
				},
				{
					"directoryIndex" : 0,
					"id" : "unitree_go__rosidl_typesupport_introspection_cpp::@6890427a1f51a3e7e1df",
					"jsonFile" : "target-unitree_go__rosidl_typesupport_introspection_cpp-b03ac1c31928312805aa.json",
					"name" : "unitree_go__rosidl_typesupport_introspection_cpp",
					"projectIndex" : 0
				},
				{
					"directoryIndex" : 0,
					"id" : "unitree_go_uninstall::@6890427a1f51a3e7e1df",
					"jsonFile" : "target-unitree_go_uninstall-86a7b4b9f97c4465996c.json",
					"name" : "unitree_go_uninstall",
					"projectIndex" : 0
				}
			]
		}
	],
	"kind" : "codemodel",
	"paths" : 
	{
		"build" : "/home/jnu/isaac_ws/build/unitree_go",
		"source" : "/home/jnu/isaac_ws/src/unitree_go"
	},
	"version" : 
	{
		"major" : 2,
		"minor" : 9
	}
}
